HISTORY.rst
LICENSE
MANIFEST.in
README.rst
setup.py
clearbit_slack/__init__.py
clearbit_slack/attachments.py
clearbit_slack/helpers.py
clearbit_slack/notifier.py
clearbit_slack_python.egg-info/PKG-INFO
clearbit_slack_python.egg-info/SOURCES.txt
clearbit_slack_python.egg-info/dependency_links.txt
clearbit_slack_python.egg-info/requires.txt
clearbit_slack_python.egg-info/top_level.txt
docs/Makefile
docs/attachments.rst
docs/conf.py
docs/helpers.rst
docs/history.rst
docs/index.rst
docs/license.rst
docs/make.bat
docs/notifier.rst
docs/_build/doctrees/attachments.doctree
docs/_build/doctrees/environment.pickle
docs/_build/doctrees/helpers.doctree
docs/_build/doctrees/history.doctree
docs/_build/doctrees/index.doctree
docs/_build/doctrees/license.doctree
docs/_build/doctrees/notifier.doctree
docs/_build/html/.buildinfo
docs/_build/html/attachments.html
docs/_build/html/genindex.html
docs/_build/html/helpers.html
docs/_build/html/history.html
docs/_build/html/index.html
docs/_build/html/license.html
docs/_build/html/notifier.html
docs/_build/html/objects.inv
docs/_build/html/py-modindex.html
docs/_build/html/search.html
docs/_build/html/searchindex.js
docs/_build/html/_sources/attachments.txt
docs/_build/html/_sources/helpers.txt
docs/_build/html/_sources/history.txt
docs/_build/html/_sources/index.txt
docs/_build/html/_sources/license.txt
docs/_build/html/_sources/notifier.txt
docs/_build/html/_static/ajax-loader.gif
docs/_build/html/_static/alabaster.css
docs/_build/html/_static/basic.css
docs/_build/html/_static/comment-bright.png
docs/_build/html/_static/comment-close.png
docs/_build/html/_static/comment.png
docs/_build/html/_static/doctools.js
docs/_build/html/_static/down-pressed.png
docs/_build/html/_static/down.png
docs/_build/html/_static/file.png
docs/_build/html/_static/jquery-1.11.1.js
docs/_build/html/_static/jquery.js
docs/_build/html/_static/minus.png
docs/_build/html/_static/plus.png
docs/_build/html/_static/pygments.css
docs/_build/html/_static/searchtools.js
docs/_build/html/_static/underscore-1.3.1.js
docs/_build/html/_static/underscore.js
docs/_build/html/_static/up-pressed.png
docs/_build/html/_static/up.png
docs/_build/html/_static/websupport.js
