Metadata-Version: 1.1
Name: clearbit-slack-python
Version: 0.1.1
Summary: Push Clearbit Person and Company data into a Slack channel
Home-page: https://github.com/15five/clearbit-slack-python
Author: Paul Logston
Author-email: code@logston.me
License: The MIT License (MIT)
